b4msa/__init__.py
b4msa/classifier.py
b4msa/command_line.py
b4msa/lang_dependency.py
b4msa/params.py
b4msa/textmodel.py
b4msa/resources/arabic.stopwords
b4msa/resources/emoticons.json
b4msa/resources/english.neg.stopwords
b4msa/resources/english.stopwords
b4msa/resources/italian.neg.stopwords
b4msa/resources/italian.stopwords
b4msa/resources/spanish.neg.stopwords
b4msa/resources/spanish.stopwords
b4msa/tests/__init__.py
b4msa/tests/test_classifier.py
b4msa/tests/test_command_line.py
b4msa/tests/test_lang_dependency.py
b4msa/tests/test_textmodel.py
b4msa/tests/text.json
b4msa-2.2.4.dist-info/LICENSE
b4msa-2.2.4.dist-info/METADATA
b4msa-2.2.4.dist-info/WHEEL
b4msa-2.2.4.dist-info/top_level.txt
b4msa-2.2.4.dist-info/RECORD
