Metadata-Version: 2.1
Name: b4msa
Version: 2.2.4
Summary: Baselines for Multilingual Sentiment Analysis
Author: Eric S. Tellez, Sabino Miranda-Jiménez, Mario Graff, Daniela Moctezuma, Ranyart R. Suárez, Oscar S. Siordia
Maintainer-email: Mario Graff <mgraffg@ieee.org>
Project-URL: Homepage, https://b4msa.readthedocs.io
Project-URL: Repository, https://github.com/INGEOTEC/b4msa
Project-URL: Issues, https://github.com/INGEOTEC/b4msa/issues
Classifier: Development Status :: 3 - Alpha
Classifier: Environment :: Console
Classifier: Intended Audience :: Science/Research
Classifier: License :: OSI Approved :: Apache Software License
Classifier: Natural Language :: English
Classifier: Operating System :: MacOS :: MacOS X
Classifier: Operating System :: POSIX :: Linux
Classifier: Programming Language :: Python :: 3
Classifier: Topic :: Scientific/Engineering :: Artificial Intelligence
License-File: LICENSE
Requires-Dist: numpy
Requires-Dist: scikit-learn>=1.3.0
Requires-Dist: microtc
